{
  "items": [
    {
      "title": "【Midjourney | Nano Banana】商品撮影のプロが撮影をやめた。誰も教えない、ブランドやECの現場レベルで使える画像生成AIと動画生成AIの神業プロンプトまとめ。｜さきすた",
      "link": "https://note.com/sakisuta/n/n5bfecc698d6c",
      "category": "hatena-bookmark-tech"
    },
    {
      "title": "品質は設計でつくり込む / design in quality",
      "link": "https://speakerdeck.com/technuma/design-in-quality",
      "category": "hatena-bookmark-tech"
    },
    {
      "title": "「AIショック」に沈むApple　「iPhone以来の革命」に乗り遅れた3つの理由 | TBS CROSS DIG with Bloomberg",
      "link": "https://newsdig.tbs.co.jp/articles/withbloomberg/2270426",
      "category": "hatena-bookmark-tech"
    },
    {
      "title": "チームのテスト力を総合的に鍛えてシフトレフトを推進する/Shifting Left with Software Testing Improvements",
      "link": "https://speakerdeck.com/goyoki/shifting-left-with-software-testing-improvements",
      "category": "hatena-bookmark-tech"
    },
    {
      "title": "海外でバズった『Googleを使わずに、最も有名な日本人の名前を挙げてください』を集計してみたら色々と興味深い結果になった",
      "link": "https://togetter.com/li/2625791",
      "category": "hatena-bookmark-tech"
    },
    {
      "title": "Affinity アプリが永久無料と聞いてこれで脱 Adobe できるかと思ってるあなたに、Affinity 歴約 5 年の私から伝えておきたいこと",
      "link": "https://jeffreyfrancesco.org/weblog/2025110501/",
      "category": "hatena-bookmark-tech"
    },
    {
      "title": "MIT、AI時代の新開発論を提唱。「可読性の高いソフトウェア」は\"バイブコーディング\"を終わらせるか | XenoSpectrum",
      "link": "https://xenospectrum.com/mit-legible-software-concepts-synchronizations-ai-coding/",
      "category": "hatena-bookmark-tech"
    },
    {
      "title": "2025年のAI活用を総まとめ！実践から振り返るTalk Night",
      "link": "https://findy.connpass.com/event/374042/?utm_campaign=series_events\u0026utm_source=feed\u0026utm_medium=atom",
      "category": "events"
    },
    {
      "title": "反イスラム感情惹起に生成AI動画が使用されることが増えてきた - 電脳塵芥",
      "link": "https://nou-yunyun.hatenablog.com/entry/2025/11/09/170000",
      "category": "hatena-bookmark-tech"
    },
    {
      "title": "Cloudflare Meet-up Tokyo Vol.9",
      "link": "https://cfm-cts.connpass.com/event/374413/?utm_campaign=series_events\u0026utm_source=feed\u0026utm_medium=atom",
      "category": "events"
    },
    {
      "title": "GeminiでAIの「ブラックボックス」を解明！実装 Tipsとプロンプト全公開 | LegalOn Technologies Engineering Blog",
      "link": "https://tech.legalforce.co.jp/entry/ai-sales-dataanalysis2",
      "category": "jsts"
    },
    {
      "title": "週刊生成AI with AWS – 2025/11/3週",
      "link": "https://aws.amazon.com/jp/blogs/news/weekly-genai-20251103/",
      "category": "cloud"
    },
    {
      "title": "例外処理を理解して、設計段階からエラーを見つけやすく、起こりにくく #phpconfuk",
      "link": "https://speakerdeck.com/kajitack/understanding-exceptions-in-php",
      "category": "hatena-bookmark-tech"
    },
    {
      "title": "RecSys 2025 参加レポート",
      "link": "https://techblog.lycorp.co.jp/ja/20251106a",
      "category": "company"
    }
  ]
}